flightgear/meta/__init__.py
flightgear/meta/exceptions.py
flightgear/meta/logging.py
flightgear/meta/lxml_utils.py
flightgear/meta/misc.py
flightgear/meta/sgprops.py
flightgear/meta/strutils.py
flightgear/meta/aircraft_catalogs/catalog.py
flightgear/meta/aircraft_catalogs/catalogTags.py
flightgear/meta/i18n/__init__.py
flightgear/meta/scripts/__init__.py
flightgear/meta/scripts/fg_validate_PropertyList.py
flightgear/meta/scripts/fg_validate_shaders.py
flightgear/meta/scripts/git_date.py
flightgear/meta/scripts/currently_unused/__init__.py
flightgear/meta/scripts/currently_unused/rebuild_fgdata_embedded_resources.py
flightgear/meta/scripts/i18n/__init__.py
flightgear/meta/scripts/i18n/fg_convert_translation_files.py
flightgear/meta/scripts/i18n/fg_copy_weather_scenarios_to_default_locale.py
flightgear/meta/scripts/i18n/fg_extract_translatable_strings.py
flightgear/meta/scripts/i18n/fg_fix_Qt_translation_files.py
flightgear/meta/scripts/i18n/fg_merge_xliff_into_xliff.py
flightgear/meta/scripts/i18n/fg_new_translations.py
flightgear/meta/scripts/i18n/fg_update_translation_files.py
flightgear/meta/scripts/terrasync/__init__.py
flightgear/meta/scripts/terrasync/create_dirindex.py
flightgear/meta/scripts/terrasync/terrasync.py
flightgear/meta/terrasync/__init__.py
flightgear/meta/terrasync/dirindex.py
flightgear/meta/terrasync/dirindexize_dir.py
flightgear/meta/terrasync/exceptions.py
flightgear/meta/terrasync/virtual_path.py
flightgear-1.0.0.dist-info/licenses/LICENSE
flightgear-1.0.0.dist-info/licenses/LICENSES/BSD-2-Clause-Views
flightgear-1.0.0.dist-info/licenses/LICENSES/GPL-2.0-or-later
flightgear-1.0.0.dist-info/METADATA
flightgear-1.0.0.dist-info/WHEEL
flightgear-1.0.0.dist-info/entry_points.txt
flightgear-1.0.0.dist-info/top_level.txt
flightgear-1.0.0.dist-info/RECORD
