Metadata-Version: 2.4
Name: FlightGear
Version: 1.0.0
Summary: Tooling for the FlightGear flight simulator
Author-email: Stuart Buchanan <stuart13@gmail.com>, Torsten Dreyer <torsten@t3r.de>, Florent Rougon <f.rougon@frougon.net>, James Turner <james@flightgear.org>
Maintainer-email: Stuart Buchanan <stuart13@gmail.com>, Torsten Dreyer <torsten@t3r.de>, Florent Rougon <f.rougon@frougon.net>, James Turner <james@flightgear.org>
License-Expression: GPL-2.0-or-later
Project-URL: Homepage, https://www.flightgear.org/
Project-URL: Repository, https://gitlab.com/flightgear/fgmeta-python/
Project-URL: Issues, https://gitlab.com/flightgear/fgmeta-python/-/issues
Keywords: FlightGear,flightgear,flight,simulator,tools
Classifier: Development Status :: 4 - Beta
Classifier: Intended Audience :: Developers
Classifier: Operating System :: OS Independent
Classifier: Programming Language :: Python :: 3
Classifier: Topic :: Games/Entertainment :: Simulation
Classifier: Topic :: Software Development :: Libraries :: Python Modules
Requires-Python: >=3.8
License-File: LICENSE
License-File: LICENSES/BSD-2-Clause-Views
License-File: LICENSES/GPL-2.0-or-later
Requires-Dist: lxml
Dynamic: license-file
